mito/__init__.py
mito/io/__init__.py
mito/io/format_afm.py
mito/io/phylo_io.py
mito/pl/__init__.py
mito/pl/diagnostic_plots.py
mito/pl/embeddings_plots.py
mito/pl/heatmaps_plots.py
mito/pl/other_plots.py
mito/pl/phylo_plots.py
mito/pp/__init__.py
mito/pp/dimred.py
mito/pp/distances.py
mito/pp/filters.py
mito/pp/kNN.py
mito/pp/preprocessing.py
mito/tl/__init__.py
mito/tl/_classification.py
mito/tl/annotate.py
mito/tl/bootstrap.py
mito/tl/clustering.py
mito/tl/phenotype.py
mito/tl/phylo.py
mito/ut/__init__.py
mito/ut/de_utils.py
mito/ut/metrics.py
mito/ut/phylo_utils.py
mito/ut/positions.py
mito/ut/stats_utils.py
mito/ut/utils.py
mito_utils-0.1.4.data/data/assets/REDIdb_MT.txt
mito_utils-0.1.4.data/data/assets/chrM.fa
mito_utils-0.1.4.data/data/assets/dbSNP_MT.txt
mito_utils-0.1.4.data/data/assets/formatted_table_wobble.csv
mito_utils-0.1.4.data/data/assets/weng2024_mut_spectrum_ref.csv
mito_utils-0.1.4.dist-info/LICENSE
mito_utils-0.1.4.dist-info/METADATA
mito_utils-0.1.4.dist-info/WHEEL
mito_utils-0.1.4.dist-info/top_level.txt
mito_utils-0.1.4.dist-info/RECORD
