Metadata-Version: 2.2
Name: mito-utils
Version: 0.1.4
Summary: Utilities for MT-based single cell Lineage Tracing (scLT).
Home-page: https://github.com/andrecossa5/MiTo
Author: Andrea Cossa
Author-email: your.email@example.com
Classifier: Programming Language :: Python :: 3
Classifier: License :: OSI Approved :: MIT License
Classifier: Operating System :: OS Independent
Requires-Python: >=3.11
License-File: LICENSE
Dynamic: author
Dynamic: author-email
Dynamic: classifier
Dynamic: description
Dynamic: description-content-type
Dynamic: home-page
Dynamic: requires-python
Dynamic: summary
